LICENSE
safety/__init__.py
safety/admin.py
safety/apps.py
safety/migrations/0001_initial.py
safety/migrations/0002_alter_objectpermission_object_ct_and_more.py
safety/migrations/0003_alter_objectpermission_options.py
safety/migrations/0004_alter_objectpermission_unique_together_and_more.py
safety/migrations/0005_alter_permissiongroup_target_id_and_more.py
safety/migrations/0006_alter_objectpermission_options.py
safety/migrations/0007_alter_objectpermission_options.py
safety/migrations/0008_rename_permissiongroup_objectgroup.py
safety/migrations/0009_alter_objectgroup_permissions_and_more.py
safety/migrations/0010_alter_objectgroupuser_options_and_more.py
safety/migrations/__init__.py
safety/models.py
safety/shortcuts.py
safety/tests.py
safety/views.py
django_object_safety-2.0.1.dist-info/LICENSE
django_object_safety-2.0.1.dist-info/METADATA
django_object_safety-2.0.1.dist-info/WHEEL
django_object_safety-2.0.1.dist-info/RECORD
