Metadata-Version: 2.1
Name: django-object-safety
Version: 2.0.1
Summary: Adds object permissions to Django.
Home-page: https://django-object-safety-docs.readthedocs.io/en/latest/
License: MIT
Keywords: django,permissions,object-permissions,django-permissions,django-object-permissions
Author: William Ferreira
Requires-Python: >=3.7
Classifier: License :: OSI Approved :: MIT License
Classifier: Programming Language :: Python :: 3
Classifier: Programming Language :: Python :: 3.7
Classifier: Programming Language :: Python :: 3.8
Classifier: Programming Language :: Python :: 3.9
Classifier: Programming Language :: Python :: 3.10
Classifier: Programming Language :: Python :: 3.11
Requires-Dist: django (>3.2)
Project-URL: Repository, https://github.com/williammferreira/django-object-safety/
